harmonypy/__init__.py
harmonypy/harmony.py
harmonypy/lisi.py
harmonypy-0.2.0.dist-info/METADATA
harmonypy-0.2.0.dist-info/WHEEL
harmonypy-0.2.0.dist-info/licenses/LICENSE
harmonypy-0.2.0.dist-info/RECORD
