Metadata-Version: 2.4
Name: harmonypy
Version: 0.2.0
Summary: A data integration algorithm.
Project-URL: Homepage, https://github.com/slowkow/harmonypy
Author-email: Kamil Slowikowski <kslowikowski@gmail.com>, John Arevalo <johnarevalo@gmail.com>
License-Expression: MIT
License-File: LICENSE
Classifier: Development Status :: 3 - Alpha
Classifier: Intended Audience :: Science/Research
Classifier: License :: OSI Approved :: GNU General Public License v3 or later (GPLv3+)
Classifier: Natural Language :: English
Classifier: Operating System :: OS Independent
Classifier: Programming Language :: Python :: 3
Classifier: Topic :: Scientific/Engineering :: Bio-Informatics
Requires-Python: >=3.9
Requires-Dist: numpy
Requires-Dist: pandas
Requires-Dist: scikit-learn
Requires-Dist: scipy
Requires-Dist: torch
